{
  "hallo": { "en": "Hello", "fa": "سلام" },
  "morgen": { "en": "Morning", "fa": "صبح" },
  "danke": { "en": "Thanks", "fa": "ممنون" },
  "bitte": { "en": "Please / You're welcome", "fa": "لطفاً / خواهش می‌کنم" },
  "ja": { "en": "Yes", "fa": "بله" },
  "nein": { "en": "No", "fa": "نه" },
  "ich": { "en": "I", "fa": "من" },
  "du": { "en": "You", "fa": "تو" },
  "sie": { "en": "You (formal) / She / They", "fa": "شما / او / آنها" },
  "er": { "en": "He", "fa": "او (مرد)" },
  "es": { "en": "It", "fa": "آن" },
  "wir": { "en": "We", "fa": "ما" },
  "ihr": { "en": "You (plural)", "fa": "شما (جمع)" },
  "helfen": { "en": "Help", "fa": "کمک کردن" },
  "problem": { "en": "Problem", "fa": "مشکل" },
  "verstehe": { "en": "Understand", "fa": "می‌فهمم" },
  "wiederholen": { "en": "Repeat", "fa": "تکرار کردن" },
  "langsammer": { "en": "Slower", "fa": "آروم‌تر" },
  "bedeutet": { "en": "Means", "fa": "یعنی" },
  "heute": { "en": "Today", "fa": "امروز" },
  "jetzt": { "en": "Now", "fa": "الان" },
  "hier": { "en": "Here", "fa": "اینجا" },
  "dort": { "en": "There", "fa": "آنجا" },
  "wo": { "en": "Where", "fa": "کجا" },
  "wann": { "en": "When", "fa": "کی" },
  "gut": { "en": "Good", "fa": "خوب" },
  "schlecht": { "en": "Bad", "fa": "بد" },
  "teuer": { "en": "Expensive", "fa": "گرون" },
  "billig": { "en": "Cheap", "fa": "ارزون" },
  "denken": { "en": "Think", "fa": "فکر کردن" },
  "idee": { "en": "Idea", "fa": "ایده" },
  "stress": { "en": "Stress", "fa": "استرس" },
  "müde": { "en": "Tired", "fa": "خسته" },
  "bin": { "en": "Am", "fa": "هستم" },
  "bist": { "en": "Are", "fa": "هستی" },
  "ist": { "en": "Is", "fa": "است" },
  "sind": { "en": "Are", "fa": "هستند" },
  "habe": { "en": "Have", "fa": "دارم" },
  "hast": { "en": "Have", "fa": "داری" },
  "hat": { "en": "Has", "fa": "دارد" },
  "haben": { "en": "Have", "fa": "داشتن" },
  "sein": { "en": "To be / His", "fa": "بودن / مال او" },
  "mein": { "en": "My", "fa": "مال من" },
  "meine": { "en": "My", "fa": "مال من" },
  "dein": { "en": "Your", "fa": "مال تو" },
  "deine": { "en": "Your", "fa": "مال تو" },
  "kein": { "en": "No / Not a", "fa": "هیچ" },
  "keine": { "en": "No / Not any", "fa": "هیچ" },
  "nicht": { "en": "Not", "fa": "نه / نیست" },
  "und": { "en": "And", "fa": "و" },
  "oder": { "en": "Or", "fa": "یا" },
  "aber": { "en": "But", "fa": "اما" },
  "auch": { "en": "Also", "fa": "همچنین" },
  "sehr": { "en": "Very", "fa": "خیلی" },
  "guten": { "en": "Good", "fa": "خوب" },
  "tag": { "en": "Day", "fa": "روز" },
  "abend": { "en": "Evening", "fa": "شب" },
  "nacht": { "en": "Night", "fa": "شب" },
  "gute": { "en": "Good", "fa": "خوب" },
  "wie": { "en": "How", "fa": "چطور" },
  "was": { "en": "What", "fa": "چه" },
  "wer": { "en": "Who", "fa": "چه کسی" },
  "warum": { "en": "Why", "fa": "چرا" },
  "geht": { "en": "Goes / Doing", "fa": "می‌رود" },
  "gehen": { "en": "To go", "fa": "رفتن" },
  "kommen": { "en": "To come", "fa": "آمدن" },
  "komme": { "en": "Come", "fa": "می‌آیم" },
  "kommst": { "en": "Come", "fa": "می‌آیی" },
  "kommt": { "en": "Comes", "fa": "می‌آید" },
  "aus": { "en": "From", "fa": "از" },
  "in": { "en": "In", "fa": "در" },
  "mit": { "en": "With", "fa": "با" },
  "zu": { "en": "To", "fa": "به" },
  "für": { "en": "For", "fa": "برای" },
  "von": { "en": "From / Of", "fa": "از" },
  "auf": { "en": "On", "fa": "روی" },
  "an": { "en": "At / On", "fa": "در / به" },
  "nach": { "en": "After / To", "fa": "بعد از / به" },
  "bei": { "en": "At / Near", "fa": "نزد / پیش" },
  "bis": { "en": "Until", "fa": "تا" },
  "über": { "en": "Over / About", "fa": "بالای / درباره" },
  "um": { "en": "At / Around", "fa": "ساعت / حول" },
  "noch": { "en": "Still / Yet", "fa": "هنوز" },
  "schon": { "en": "Already", "fa": "قبلاً" },
  "nur": { "en": "Only", "fa": "فقط" },
  "immer": { "en": "Always", "fa": "همیشه" },
  "nie": { "en": "Never", "fa": "هرگز" },
  "name": { "en": "Name", "fa": "نام" },
  "heißen": { "en": "To be called", "fa": "نامیده شدن" },
  "heiße": { "en": "Am called", "fa": "نامم هست" },
  "heißt": { "en": "Is called", "fa": "نامش هست" },
  "sprechen": { "en": "To speak", "fa": "صحبت کردن" },
  "spreche": { "en": "Speak", "fa": "صحبت می‌کنم" },
  "sprichst": { "en": "Speak", "fa": "صحبت می‌کنی" },
  "spricht": { "en": "Speaks", "fa": "صحبت می‌کند" },
  "deutsch": { "en": "German", "fa": "آلمانی" },
  "englisch": { "en": "English", "fa": "انگلیسی" },
  "persisch": { "en": "Persian", "fa": "فارسی" },
  "ein": { "en": "A / One", "fa": "یک" },
  "eine": { "en": "A / One", "fa": "یک" },
  "einen": { "en": "A / One (accusative)", "fa": "یک" },
  "der": { "en": "The (masc.)", "fa": "آن (مذکر)" },
  "die": { "en": "The (fem./plural)", "fa": "آن (مؤنث/جمع)" },
  "das": { "en": "The (neut.)", "fa": "آن (خنثی)" },
  "den": { "en": "The (accusative)", "fa": "آن (مفعولی)" },
  "dem": { "en": "The (dative)", "fa": "آن (اضافی)" },
  "können": { "en": "Can / To be able", "fa": "توانستن" },
  "kann": { "en": "Can", "fa": "می‌توانم" },
  "kannst": { "en": "Can", "fa": "می‌توانی" },
  "möchte": { "en": "Would like", "fa": "می‌خواهم" },
  "möchten": { "en": "Would like", "fa": "می‌خواهید" },
  "muss": { "en": "Must", "fa": "باید" },
  "müssen": { "en": "Must", "fa": "باید" },
  "will": { "en": "Want", "fa": "می‌خواهم" },
  "wollen": { "en": "Want", "fa": "خواستن" },
  "soll": { "en": "Should", "fa": "باید" },
  "sollen": { "en": "Should", "fa": "باید" },
  "darf": { "en": "May / Allowed to", "fa": "اجازه دارم" },
  "dürfen": { "en": "May / To be allowed", "fa": "اجازه داشتن" },
  "brauche": { "en": "Need", "fa": "نیاز دارم" },
  "brauchen": { "en": "To need", "fa": "نیاز داشتن" },
  "wissen": { "en": "To know", "fa": "دانستن" },
  "weiß": { "en": "Know", "fa": "می‌دانم" },
  "kennen": { "en": "To know (person/place)", "fa": "شناختن" },
  "machen": { "en": "To do / To make", "fa": "انجام دادن / ساختن" },
  "nehmen": { "en": "To take", "fa": "گرفتن" },
  "nehme": { "en": "Take", "fa": "می‌گیرم" },
  "geben": { "en": "To give", "fa": "دادن" },
  "gibt": { "en": "Gives / There is", "fa": "می‌دهد / هست" },
  "sehen": { "en": "To see", "fa": "دیدن" },
  "sagen": { "en": "To say", "fa": "گفتن" },
  "fragen": { "en": "To ask", "fa": "پرسیدن" },
  "finde": { "en": "Find / Think", "fa": "پیدا می‌کنم" },
  "finden": { "en": "To find", "fa": "پیدا کردن" },
  "kaufen": { "en": "To buy", "fa": "خریدن" },
  "bezahlen": { "en": "To pay", "fa": "پرداخت کردن" },
  "zahlen": { "en": "To pay", "fa": "پرداخت کردن" },
  "kosten": { "en": "To cost", "fa": "قیمت داشتن" },
  "kostet": { "en": "Costs", "fa": "قیمتش هست" },
  "essen": { "en": "To eat", "fa": "خوردن" },
  "trinken": { "en": "To drink", "fa": "نوشیدن" },
  "wohnen": { "en": "To live (reside)", "fa": "زندگی کردن" },
  "wohne": { "en": "Live (reside)", "fa": "زندگی می‌کنم" },
  "arbeiten": { "en": "To work", "fa": "کار کردن" },
  "arbeite": { "en": "Work", "fa": "کار می‌کنم" },
  "lernen": { "en": "To learn", "fa": "یاد گرفتن" },
  "lerne": { "en": "Learn", "fa": "یاد می‌گیرم" },
  "suche": { "en": "Search / Look for", "fa": "دنبال می‌گردم" },
  "suchen": { "en": "To search", "fa": "جستجو کردن" },
  "warten": { "en": "To wait", "fa": "صبر کردن" },
  "fahren": { "en": "To drive / To go (vehicle)", "fa": "رانندگی کردن" },
  "fährt": { "en": "Drives / Goes", "fa": "می‌رود" },
  "karte": { "en": "Card / Ticket / Map", "fa": "کارت / بلیط / نقشه" },
  "ticket": { "en": "Ticket", "fa": "بلیط" },
  "straße": { "en": "Street", "fa": "خیابان" },
  "platz": { "en": "Place / Square", "fa": "جا / میدان" },
  "stadt": { "en": "City", "fa": "شهر" },
  "haus": { "en": "House", "fa": "خانه" },
  "wohnung": { "en": "Apartment", "fa": "آپارتمان" },
  "zimmer": { "en": "Room", "fa": "اتاق" },
  "tür": { "en": "Door", "fa": "در" },
  "fenster": { "en": "Window", "fa": "پنجره" },
  "schule": { "en": "School", "fa": "مدرسه" },
  "kurs": { "en": "Course", "fa": "دوره" },
  "termin": { "en": "Appointment", "fa": "وقت ملاقات" },
  "arzt": { "en": "Doctor", "fa": "دکتر" },
  "krankenhaus": { "en": "Hospital", "fa": "بیمارستان" },
  "apotheke": { "en": "Pharmacy", "fa": "داروخانه" },
  "geld": { "en": "Money", "fa": "پول" },
  "euro": { "en": "Euro", "fa": "یورو" },
  "preis": { "en": "Price", "fa": "قیمت" },
  "nummer": { "en": "Number", "fa": "شماره" },
  "telefon": { "en": "Phone", "fa": "تلفن" },
  "handy": { "en": "Mobile phone", "fa": "موبایل" },
  "uhr": { "en": "Clock / O'clock", "fa": "ساعت" },
  "zeit": { "en": "Time", "fa": "وقت" },
  "minute": { "en": "Minute", "fa": "دقیقه" },
  "stunde": { "en": "Hour", "fa": "ساعت" },
  "woche": { "en": "Week", "fa": "هفته" },
  "monat": { "en": "Month", "fa": "ماه" },
  "jahr": { "en": "Year", "fa": "سال" },
  "montag": { "en": "Monday", "fa": "دوشنبه" },
  "dienstag": { "en": "Tuesday", "fa": "سه‌شنبه" },
  "mittwoch": { "en": "Wednesday", "fa": "چهارشنبه" },
  "donnerstag": { "en": "Thursday", "fa": "پنجشنبه" },
  "freitag": { "en": "Friday", "fa": "جمعه" },
  "samstag": { "en": "Saturday", "fa": "شنبه" },
  "sonntag": { "en": "Sunday", "fa": "یکشنبه" },
  "mann": { "en": "Man / Husband", "fa": "مرد / شوهر" },
  "frau": { "en": "Woman / Wife / Mrs.", "fa": "زن / خانم" },
  "kind": { "en": "Child", "fa": "بچه" },
  "kinder": { "en": "Children", "fa": "بچه‌ها" },
  "familie": { "en": "Family", "fa": "خانواده" },
  "freund": { "en": "Friend", "fa": "دوست" },
  "leute": { "en": "People", "fa": "مردم" },
  "arbeit": { "en": "Work / Job", "fa": "کار" },
  "beruf": { "en": "Profession", "fa": "حرفه" },
  "wasser": { "en": "Water", "fa": "آب" },
  "kaffee": { "en": "Coffee", "fa": "قهوه" },
  "tee": { "en": "Tea", "fa": "چای" },
  "brot": { "en": "Bread", "fa": "نان" },
  "essen": { "en": "Food / To eat", "fa": "غذا / خوردن" },
  "groß": { "en": "Big / Tall", "fa": "بزرگ" },
  "klein": { "en": "Small / Short", "fa": "کوچک" },
  "neu": { "en": "New", "fa": "جدید" },
  "alt": { "en": "Old", "fa": "قدیمی / پیر" },
  "schön": { "en": "Beautiful / Nice", "fa": "زیبا / قشنگ" },
  "richtig": { "en": "Correct / Right", "fa": "درست" },
  "falsch": { "en": "Wrong / False", "fa": "غلط" },
  "schnell": { "en": "Fast", "fa": "سریع" },
  "langsam": { "en": "Slow", "fa": "آهسته" },
  "wirklich": { "en": "Really", "fa": "واقعاً" },
  "natürlich": { "en": "Of course", "fa": "البته" },
  "genau": { "en": "Exactly", "fa": "دقیقاً" },
  "vielleicht": { "en": "Maybe", "fa": "شاید" },
  "bestimmt": { "en": "Certainly", "fa": "حتماً" },
  "gerne": { "en": "Gladly / With pleasure", "fa": "با کمال میل" },
  "gern": { "en": "Gladly", "fa": "با کمال میل" },
  "leider": { "en": "Unfortunately", "fa": "متأسفانه" },
  "trotzdem": { "en": "Nevertheless", "fa": "با این حال" },
  "viel": { "en": "Much / A lot", "fa": "زیاد" },
  "viele": { "en": "Many", "fa": "زیاد / خیلی‌ها" },
  "wenig": { "en": "Little / Few", "fa": "کم" },
  "alle": { "en": "All / Everyone", "fa": "همه" },
  "alles": { "en": "Everything", "fa": "همه چیز" },
  "etwas": { "en": "Something / Some", "fa": "چیزی / کمی" },
  "nichts": { "en": "Nothing", "fa": "هیچ چیز" },
  "dann": { "en": "Then", "fa": "بعد / سپس" },
  "also": { "en": "So / Therefore", "fa": "پس / بنابراین" },
  "wenn": { "en": "If / When", "fa": "اگر / وقتی" },
  "dass": { "en": "That (conjunction)", "fa": "که" },
  "weil": { "en": "Because", "fa": "چون" },
  "ob": { "en": "Whether / If", "fa": "آیا" },
  "okay": { "en": "Okay", "fa": "باشه" },
  "super": { "en": "Super / Great", "fa": "عالی" },
  "prima": { "en": "Great", "fa": "عالی" },
  "toll": { "en": "Great / Awesome", "fa": "عالی" },
  "perfekt": { "en": "Perfect", "fa": "عالی" },
  "entschuldigung": { "en": "Excuse me / Sorry", "fa": "ببخشید" },
  "tschüss": { "en": "Bye", "fa": "خداحافظ" },
  "wiedersehen": { "en": "Goodbye", "fa": "خداحافظ" },
  "willkommen": { "en": "Welcome", "fa": "خوش آمدید" },
  "bald": { "en": "Soon", "fa": "به زودی" },
  "gestern": { "en": "Yesterday", "fa": "دیروز" },
  "morgens": { "en": "In the morning", "fa": "صبح‌ها" },
  "abends": { "en": "In the evening", "fa": "شب‌ها" },
  "zusammen": { "en": "Together", "fa": "با هم" },
  "allein": { "en": "Alone", "fa": "تنها" },
  "fertig": { "en": "Done / Ready", "fa": "تمام / آماده" },
  "frei": { "en": "Free", "fa": "آزاد / خالی" },
  "wichtig": { "en": "Important", "fa": "مهم" },
  "möglich": { "en": "Possible", "fa": "ممکن" },
  "offen": { "en": "Open", "fa": "باز" },
  "geschlossen": { "en": "Closed", "fa": "بسته" },
  "links": { "en": "Left", "fa": "چپ" },
  "rechts": { "en": "Right", "fa": "راست" },
  "geradeaus": { "en": "Straight ahead", "fa": "مستقیم" },
  "oben": { "en": "Up / Above", "fa": "بالا" },
  "unten": { "en": "Down / Below", "fa": "پایین" },
  "neben": { "en": "Next to", "fa": "کنار" },
  "zwischen": { "en": "Between", "fa": "بین" },
  "vor": { "en": "Before / In front of", "fa": "قبل / جلوی" },
  "hinter": { "en": "Behind", "fa": "پشت" },
  "schreiben": { "en": "To write", "fa": "نوشتن" },
  "lesen": { "en": "To read", "fa": "خواندن" },
  "verstehen": { "en": "To understand", "fa": "فهمیدن" },
  "anrufen": { "en": "To call (phone)", "fa": "زنگ زدن" },
  "rufen": { "en": "To call", "fa": "صدا زدن" },
  "öffnen": { "en": "To open", "fa": "باز کردن" },
  "schließen": { "en": "To close", "fa": "بستن" },
  "beginnen": { "en": "To begin", "fa": "شروع کردن" },
  "anfangen": { "en": "To start", "fa": "شروع کردن" },
  "aufhören": { "en": "To stop", "fa": "متوقف شدن" },
  "bleiben": { "en": "To stay", "fa": "ماندن" },
  "stehen": { "en": "To stand", "fa": "ایستادن" },
  "sitzen": { "en": "To sit", "fa": "نشستن" },
  "liegen": { "en": "To lie (position)", "fa": "دراز کشیدن" },
  "bringen": { "en": "To bring", "fa": "آوردن" },
  "zeigen": { "en": "To show", "fa": "نشان دادن" },
  "tragen": { "en": "To carry / To wear", "fa": "حمل کردن / پوشیدن" },
  "laufen": { "en": "To walk / To run", "fa": "راه رفتن / دویدن" },
  "spielen": { "en": "To play", "fa": "بازی کردن" },
  "leben": { "en": "To live", "fa": "زندگی کردن" },
  "glauben": { "en": "To believe", "fa": "باور داشتن" },
  "versuchen": { "en": "To try", "fa": "تلاش کردن" },
  "erklären": { "en": "To explain", "fa": "توضیح دادن" },
  "benutzen": { "en": "To use", "fa": "استفاده کردن" },
  "miete": { "en": "Rent", "fa": "اجاره" },
  "vertrag": { "en": "Contract", "fa": "قرارداد" },
  "unterschreiben": { "en": "To sign", "fa": "امضا کردن" },
  "ausweis": { "en": "ID card", "fa": "کارت شناسایی" },
  "pass": { "en": "Passport", "fa": "پاسپورت" },
  "anmeldung": { "en": "Registration", "fa": "ثبت‌نام" },
  "formular": { "en": "Form", "fa": "فرم" },
  "unterlagen": { "en": "Documents", "fa": "مدارک" },
  "versicherung": { "en": "Insurance", "fa": "بیمه" },
  "konto": { "en": "Account", "fa": "حساب" },
  "bank": { "en": "Bank", "fa": "بانک" },
  "brief": { "en": "Letter", "fa": "نامه" },
  "paket": { "en": "Package", "fa": "بسته" },
  "post": { "en": "Post / Mail", "fa": "پست" },
  "zug": { "en": "Train", "fa": "قطار" },
  "bus": { "en": "Bus", "fa": "اتوبوس" },
  "bahn": { "en": "Train / Railway", "fa": "قطار / راه‌آهن" },
  "flughafen": { "en": "Airport", "fa": "فرودگاه" },
  "bahnhof": { "en": "Train station", "fa": "ایستگاه قطار" },
  "haltestelle": { "en": "Stop (bus/tram)", "fa": "ایستگاه" },
  "gleis": { "en": "Platform / Track", "fa": "سکو" },
  "abfahrt": { "en": "Departure", "fa": "حرکت" },
  "ankunft": { "en": "Arrival", "fa": "رسیدن" },
  "umsteigen": { "en": "To transfer / Change", "fa": "عوض کردن" },
  "fahrkarte": { "en": "Ticket (transport)", "fa": "بلیط" },
  "hin": { "en": "There (direction)", "fa": "به آنجا" },
  "zurück": { "en": "Back", "fa": "برگشت" },
  "richtung": { "en": "Direction", "fa": "جهت" },
  "auto": { "en": "Car", "fa": "ماشین" },
  "fahrrad": { "en": "Bicycle", "fa": "دوچرخه" },
  "arztpraxis": { "en": "Doctor's office", "fa": "مطب" },
  "schmerzen": { "en": "Pain", "fa": "درد" },
  "kopfschmerzen": { "en": "Headache", "fa": "سردرد" },
  "fieber": { "en": "Fever", "fa": "تب" },
  "medikament": { "en": "Medication", "fa": "دارو" },
  "rezept": { "en": "Prescription / Recipe", "fa": "نسخه / دستورپخت" },
  "gesund": { "en": "Healthy", "fa": "سالم" },
  "krank": { "en": "Sick", "fa": "بیمار" },
  "hilfe": { "en": "Help", "fa": "کمک" },
  "polizei": { "en": "Police", "fa": "پلیس" },
  "feuerwehr": { "en": "Fire department", "fa": "آتش‌نشانی" },
  "notfall": { "en": "Emergency", "fa": "اورژانس" },
  "gefahr": { "en": "Danger", "fa": "خطر" },
  "sicher": { "en": "Safe / Sure", "fa": "امن / مطمئن" },
  "supermarkt": { "en": "Supermarket", "fa": "سوپرمارکت" },
  "laden": { "en": "Shop / Store", "fa": "مغازه" },
  "markt": { "en": "Market", "fa": "بازار" },
  "restaurant": { "en": "Restaurant", "fa": "رستوران" },
  "frühstück": { "en": "Breakfast", "fa": "صبحانه" },
  "mittagessen": { "en": "Lunch", "fa": "ناهار" },
  "abendessen": { "en": "Dinner", "fa": "شام" },
  "rechnung": { "en": "Bill / Invoice", "fa": "صورتحساب" },
  "bestellen": { "en": "To order", "fa": "سفارش دادن" },
  "möbel": { "en": "Furniture", "fa": "مبلمان" },
  "küche": { "en": "Kitchen", "fa": "آشپزخانه" },
  "bad": { "en": "Bathroom", "fa": "حمام" },
  "schlafzimmer": { "en": "Bedroom", "fa": "اتاق خواب" },
  "wohnzimmer": { "en": "Living room", "fa": "اتاق نشیمن" },
  "erdgeschoss": { "en": "Ground floor", "fa": "طبقه همکف" },
  "stock": { "en": "Floor / Story", "fa": "طبقه" },
  "aufzug": { "en": "Elevator", "fa": "آسانسور" },
  "treppe": { "en": "Stairs", "fa": "پله" },
  "mieter": { "en": "Tenant", "fa": "مستأجر" },
  "vermieter": { "en": "Landlord", "fa": "صاحبخانه" },
  "kaution": { "en": "Deposit", "fa": "ودیعه" },
  "warm": { "en": "Warm", "fa": "گرم" },
  "kalt": { "en": "Cold", "fa": "سرد" },
  "heizung": { "en": "Heating", "fa": "بخاری" },
  "strom": { "en": "Electricity", "fa": "برق" },
  "internet": { "en": "Internet", "fa": "اینترنت" },
  "firma": { "en": "Company", "fa": "شرکت" },
  "chef": { "en": "Boss", "fa": "رئیس" },
  "kollege": { "en": "Colleague", "fa": "همکار" },
  "gehalt": { "en": "Salary", "fa": "حقوق" },
  "urlaub": { "en": "Vacation", "fa": "مرخصی" },
  "bewerbung": { "en": "Application (job)", "fa": "درخواست کار" },
  "lebenslauf": { "en": "Resume / CV", "fa": "رزومه" },
  "vorstellungsgespräch": { "en": "Job interview", "fa": "مصاحبه کاری" },
  "erfahrung": { "en": "Experience", "fa": "تجربه" },
  "ausbildung": { "en": "Training / Education", "fa": "آموزش" },
  "praktikum": { "en": "Internship", "fa": "کارآموزی" },
  "zeugnis": { "en": "Certificate / Report", "fa": "گواهی" },
  "amt": { "en": "Office (government)", "fa": "اداره" },
  "behörde": { "en": "Authority", "fa": "مرجع" },
  "antrag": { "en": "Application (form)", "fa": "درخواست" },
  "aufenthaltstitel": { "en": "Residence permit", "fa": "اجازه اقامت" },
  "integrationskurs": { "en": "Integration course", "fa": "دوره ادغام" },
  "kindergarten": { "en": "Kindergarten", "fa": "مهدکودک" },
  "grundschule": { "en": "Primary school", "fa": "دبستان" },
  "gymnasium": { "en": "Grammar school", "fa": "دبیرستان" },
  "universität": { "en": "University", "fa": "دانشگاه" },
  "unterricht": { "en": "Class / Lesson", "fa": "درس / کلاس" },
  "prüfung": { "en": "Exam", "fa": "امتحان" },
  "hausaufgaben": { "en": "Homework", "fa": "تکالیف" },
  "lehrer": { "en": "Teacher", "fa": "معلم" },
  "schüler": { "en": "Student (school)", "fa": "دانش‌آموز" },

  "ihnen": { "en": "You (formal) / Them (dative)", "fa": "به شما / به آنها" },
  "mich": { "en": "Me / Myself (accusative)", "fa": "مرا / خودم" },
  "mir": { "en": "Me / To me (dative)", "fa": "به من" },
  "uns": { "en": "Us", "fa": "ما را / به ما" },
  "dich": { "en": "You (accusative)", "fa": "تو را" },
  "ihn": { "en": "Him / It (accusative)", "fa": "او را / آن را" },
  "ihm": { "en": "Him / It (dative)", "fa": "به او / به آن" },
  "sich": { "en": "Oneself / Themselves", "fa": "خود" },

  "pro": { "en": "Per", "fa": "به ازای هر" },
  "wäre": { "en": "Would be", "fa": "خواهد بود" },
  "ware": { "en": "Would be", "fa": "خواهد بود" },
  "lass": { "en": "Let (imperative)", "fa": "بگذار" },
  "lassen": { "en": "To let / To leave", "fa": "گذاشتن" },
  "später": { "en": "Later", "fa": "بعداً" },
  "spater": { "en": "Later", "fa": "بعداً" },
  "lange": { "en": "Long (duration)", "fa": "طولانی" },
  "schicken": { "en": "To send", "fa": "فرستادن" },
  "inklusive": { "en": "Included / Inclusive", "fa": "شامل" },
  "diese": { "en": "This / These", "fa": "این / اینها" },
  "dieser": { "en": "This (masc.)", "fa": "این" },
  "dieses": { "en": "This (neut.)", "fa": "این" },
  "kreditkarte": { "en": "Credit card", "fa": "کارت اعتباری" },

  "im": { "en": "In the", "fa": "در" },
  "welche": { "en": "Which", "fa": "کدام" },
  "welcher": { "en": "Which (masc.)", "fa": "کدام" },
  "welches": { "en": "Which (neut.)", "fa": "کدام" },
  "selbst": { "en": "Self / Oneself", "fa": "خود" },
  "war": { "en": "Was", "fa": "بود" },
  "als": { "en": "As / Than / When", "fa": "به عنوان / از / وقتی" },
  "zum": { "en": "To the", "fa": "به" },
  "zur": { "en": "To the (fem.)", "fa": "به" },
  "des": { "en": "Of the", "fa": "از" },
  "diesem": { "en": "This (dative)", "fa": "این" },
  "so": { "en": "So / Like this", "fa": "اینطوری / پس" },
  "oft": { "en": "Often", "fa": "اغلب" },
  "wird": { "en": "Will / Becomes", "fa": "می‌شود / خواهد" },
  "würde": { "en": "Would", "fa": "خواهد / می‌خواست" },
  "wurde": { "en": "Was / Became", "fa": "شد" },

  "biegen": { "en": "To turn", "fa": "پیچیدن" },
  "dauert": { "en": "Takes (time) / Lasts", "fa": "طول می‌کشد" },
  "dauern": { "en": "To last / To take time", "fa": "طول کشیدن" },
  "gefällt": { "en": "Pleases / Like", "fa": "خوشایند است" },
  "gefallen": { "en": "To please / To like", "fa": "خوشایند بودن" },
  "funktioniert": { "en": "Works / Functions", "fa": "کار می‌کند" },
  "funktionieren": { "en": "To work / To function", "fa": "کار کردن" },
  "treffen": { "en": "To meet", "fa": "ملاقات کردن" },
  "fühle": { "en": "Feel (1st person)", "fa": "احساس می‌کنم" },
  "fühlen": { "en": "To feel", "fa": "احساس کردن" },
  "melde": { "en": "Report / Register", "fa": "اعلام می‌کنم" },
  "melden": { "en": "To report / To register", "fa": "اعلام کردن" },
  "bekommen": { "en": "To get / To receive", "fa": "دریافت کردن" },
  "tun": { "en": "To do", "fa": "انجام دادن" },
  "tut": { "en": "Does (es tut mir leid)", "fa": "می‌کند" },
  "mag": { "en": "Like", "fa": "دوست دارم" },
  "mögen": { "en": "To like", "fa": "دوست داشتن" },
  "freut": { "en": "Pleases (freut mich)", "fa": "خوشحال می‌کند" },
  "freue": { "en": "Am glad", "fa": "خوشحالم" },
  "freuen": { "en": "To be glad", "fa": "خوشحال شدن" },
  "anmelden": { "en": "To register / To sign up", "fa": "ثبت‌نام کردن" },
  "passiert": { "en": "Happened / Happens", "fa": "اتفاق افتاد" },

  "milch": { "en": "Milk", "fa": "شیر" },
  "zucker": { "en": "Sugar", "fa": "شکر" },
  "schlüssel": { "en": "Key", "fa": "کلید" },
  "schnitzel": { "en": "Schnitzel", "fa": "شنیتسل" },
  "jacke": { "en": "Jacket", "fa": "ژاکت" },
  "größe": { "en": "Size", "fa": "اندازه" },
  "grosse": { "en": "Size", "fa": "اندازه" },
  "kino": { "en": "Cinema", "fa": "سینما" },
  "linie": { "en": "Line (transport)", "fa": "خط" },
  "reisepass": { "en": "Passport", "fa": "گذرنامه" },
  "girokonto": { "en": "Checking account", "fa": "حساب جاری" },
  "führerschein": { "en": "Driver's license", "fa": "گواهینامه" },
  "fuhrerschein": { "en": "Driver's license", "fa": "گواهینامه" },
  "geburtstag": { "en": "Birthday", "fa": "تولد" },
  "teilnehmer": { "en": "Participant", "fa": "شرکت‌کننده" },
  "gruppe": { "en": "Group", "fa": "گروه" },
  "geldbeutel": { "en": "Wallet", "fa": "کیف پول" },
  "allergien": { "en": "Allergies", "fa": "آلرژی‌ها" },

  "klar": { "en": "Clear / Sure", "fa": "روشن / البته" },
  "nächste": { "en": "Next", "fa": "بعدی" },
  "nachste": { "en": "Next", "fa": "بعدی" },
  "dabei": { "en": "With it / There", "fa": "همراه / در آن" },
  "weit": { "en": "Far", "fa": "دور" },
  "gerade": { "en": "Right now / Just", "fa": "الان / درست" },
  "direkt": { "en": "Direct(ly)", "fa": "مستقیم" },
  "sofort": { "en": "Immediately", "fa": "فوراً" },
  "ungefähr": { "en": "Approximately", "fa": "تقریباً" },
  "ungefahr": { "en": "Approximately", "fa": "تقریباً" },
  "verfügbar": { "en": "Available", "fa": "موجود" },
  "verfugbar": { "en": "Available", "fa": "موجود" },
  "voll": { "en": "Full", "fa": "پر" },
  "herzlichen": { "en": "Heartfelt / Cordial", "fa": "صمیمانه" },
  "nächte": { "en": "Nights", "fa": "شب‌ها" },

  "geschehen": { "en": "To happen (gern geschehen = you're welcome)", "fa": "اتفاق افتادن / خواهش می‌کنم" },
  "kennenzulernen": { "en": "To get to know", "fa": "آشنا شدن" },
  "kennenlernen": { "en": "To get to know", "fa": "آشنا شدن" },
  "statt": { "en": "Instead / Place", "fa": "به جای" },
  "stattfinden": { "en": "To take place", "fa": "برگزار شدن" },

  "wetter": { "en": "Weather", "fa": "آب و هوا" },
  "sonne": { "en": "Sun", "fa": "خورشید" },
  "scheint": { "en": "Shines / Seems", "fa": "می‌درخشد / به نظر می‌رسد" },
  "scheinen": { "en": "To shine / To seem", "fa": "درخشیدن / به نظر رسیدن" },
  "stimmt": { "en": "Is correct / Right", "fa": "درسته" },
  "stimmen": { "en": "To be correct", "fa": "درست بودن" },
  "windig": { "en": "Windy", "fa": "بادی" },
  "regenschirm": { "en": "Umbrella", "fa": "چتر" },

  "kreuzung": { "en": "Intersection", "fa": "چهارراه" },
  "nah": { "en": "Near / Close", "fa": "نزدیک" },
  "gegenüber": { "en": "Opposite / Across from", "fa": "روبرو" },
  "gegenuber": { "en": "Opposite / Across from", "fa": "روبرو" },
  "hauptbahnhof": { "en": "Main train station", "fa": "ایستگاه مرکزی" },
  "einzelfahrt": { "en": "Single trip", "fa": "بلیط یک‌سره" },
  "automat": { "en": "Machine / Vending machine", "fa": "دستگاه" },
  "drüben": { "en": "Over there", "fa": "آن طرف" },
  "auskunft": { "en": "Information", "fa": "اطلاعات" },

  "kurz": { "en": "Short / Briefly", "fa": "کوتاه / مختصر" },
  "vorstellen": { "en": "To introduce / To imagine", "fa": "معرفی کردن / تصور کردن" },
  "ursprünglich": { "en": "Originally", "fa": "اصلاً" },
  "freizeit": { "en": "Free time", "fa": "وقت آزاد" },
  "fußball": { "en": "Football / Soccer", "fa": "فوتبال" },
  "fussball": { "en": "Football / Soccer", "fa": "فوتبال" },
  "reise": { "en": "Journey / Trip", "fa": "سفر" },
  "reisen": { "en": "To travel", "fa": "سفر کردن" },
  "woher": { "en": "Where from", "fa": "از کجا" },
  "nett": { "en": "Nice / Kind", "fa": "مهربان" },
  "mehr": { "en": "More", "fa": "بیشتر" },
  "nachdenken": { "en": "To think about", "fa": "فکر کردن" },
  "los": { "en": "Go / Off / Let's go", "fa": "شروع / بزن بریم" },
  "nochmal": { "en": "Once more / Again", "fa": "دوباره" },

  "beschäftigt": { "en": "Busy", "fa": "مشغول" },
  "beschaftigt": { "en": "Busy", "fa": "مشغول" },
  "ausruhen": { "en": "To rest", "fa": "استراحت کردن" },
  "besprechung": { "en": "Meeting", "fa": "جلسه" },
  "besser": { "en": "Better", "fa": "بهتر" },
  "gestresst": { "en": "Stressed", "fa": "استرس‌دار" },
  "pause": { "en": "Break / Pause", "fa": "وقفه / استراحت" },
  "spät": { "en": "Late", "fa": "دیر" },
  "spat": { "en": "Late", "fa": "دیر" },

  "bargeld": { "en": "Cash", "fa": "پول نقد" },
  "tisch": { "en": "Table", "fa": "میز" },
  "speisekarte": { "en": "Menu", "fa": "منو" },
  "empfehlen": { "en": "To recommend", "fa": "توصیه کردن" },
  "empfehle": { "en": "Recommend", "fa": "توصیه می‌کنم" },
  "glas": { "en": "Glass", "fa": "لیوان" },
  "appetit": { "en": "Appetite", "fa": "اشتها" },
  "beliebt": { "en": "Popular", "fa": "محبوب" },
  "anprobieren": { "en": "To try on", "fa": "امتحان کردن (لباس)" },
  "umkleidekabine": { "en": "Fitting room", "fa": "اتاق پرو" },
  "bäckerei": { "en": "Bakery", "fa": "نانوایی" },
  "backerei": { "en": "Bakery", "fa": "نانوایی" },
  "tüte": { "en": "Bag", "fa": "کیسه" },
  "tute": { "en": "Bag", "fa": "کیسه" },
  "bar": { "en": "Cash / Bar", "fa": "نقدی / بار" },

  "verpasst": { "en": "Missed", "fa": "از دست دادم" },
  "verpassen": { "en": "To miss", "fa": "از دست دادن" },
  "flug": { "en": "Flight", "fa": "پرواز" },
  "verspätung": { "en": "Delay", "fa": "تأخیر" },
  "verspatung": { "en": "Delay", "fa": "تأخیر" },
  "information": { "en": "Information", "fa": "اطلاعات" },

  "fehlt": { "en": "Is missing / Lacks", "fa": "نیست / کم دارد" },
  "fehlen": { "en": "To be missing", "fa": "نبودن / کم بودن" },
  "gegen": { "en": "Against / Around (time)", "fa": "علیه / حدود" },
  "tabletten": { "en": "Tablets / Pills", "fa": "قرص‌ها" },
  "tablette": { "en": "Tablet / Pill", "fa": "قرص" },
  "täglich": { "en": "Daily", "fa": "روزانه" },
  "taglich": { "en": "Daily", "fa": "روزانه" },
  "vitamine": { "en": "Vitamins", "fa": "ویتامین‌ها" },
  "regal": { "en": "Shelf", "fa": "قفسه" },

  "eröffnen": { "en": "To open (account)", "fa": "افتتاح کردن" },
  "eroffnen": { "en": "To open (account)", "fa": "افتتاح کردن" },
  "sparkonto": { "en": "Savings account", "fa": "حساب پس‌انداز" },

  "moment": { "en": "Moment", "fa": "لحظه" },
  "verbinde": { "en": "Connect (1st person)", "fa": "وصل می‌کنم" },
  "verbinden": { "en": "To connect", "fa": "وصل کردن" },
  "nachricht": { "en": "Message", "fa": "پیام" },
  "hinterlassen": { "en": "To leave (message)", "fa": "گذاشتن (پیام)" },
  "ausrichten": { "en": "To pass on (message)", "fa": "رساندن (پیام)" },
  "angerufen": { "en": "Called (phone)", "fa": "زنگ زده" },

  "halb": { "en": "Half", "fa": "نیم" },
  "mitbringen": { "en": "To bring along", "fa": "با خود آوردن" },
  "wein": { "en": "Wine", "fa": "شراب" },
  "glückwunsch": { "en": "Congratulations", "fa": "تبریک" },
  "gluckwunsch": { "en": "Congratulations", "fa": "تبریک" },
  "hoffe": { "en": "Hope (1st person)", "fa": "امیدوارم" },
  "hoffen": { "en": "To hope", "fa": "امیدوار بودن" },
  "dir": { "en": "You (dative informal)", "fa": "به تو" },
  "doch": { "en": "But / Yet / Indeed", "fa": "ولی / آره" },
  "nötig": { "en": "Necessary", "fa": "لازم" },
  "notig": { "en": "Necessary", "fa": "لازم" },
  "gewesen": { "en": "Been (past participle)", "fa": "بوده" },
  "werde": { "en": "Will / Become", "fa": "خواهم / می‌شوم" },
  "werden": { "en": "Will / To become", "fa": "خواهد / شدن" },
  "kaum": { "en": "Hardly / Barely", "fa": "به سختی" },
  "kuchen": { "en": "Cake", "fa": "کیک" },
  "sieht": { "en": "Looks / Sees", "fa": "می‌بیند / به نظر می‌رسد" },
  "mutter": { "en": "Mother", "fa": "مادر" },
  "vater": { "en": "Father", "fa": "پدر" },
  "schokolade": { "en": "Chocolate", "fa": "شکلات" },
  "anstoßen": { "en": "To toast / To clink glasses", "fa": "به سلامتی نوشیدن" },
  "anstossen": { "en": "To toast / To clink glasses", "fa": "به سلامتی نوشیدن" },
  "gesundheit": { "en": "Health / Bless you", "fa": "سلامتی" },
  "prost": { "en": "Cheers", "fa": "به سلامتی" },
  "einladung": { "en": "Invitation", "fa": "دعوت" },
  "gekommen": { "en": "Come (past participle)", "fa": "آمده" },

  "erzählen": { "en": "To tell / To narrate", "fa": "تعریف کردن" },
  "erzahlen": { "en": "To tell / To narrate", "fa": "تعریف کردن" },
  "bereich": { "en": "Area / Field", "fa": "حوزه / بخش" },
  "stärken": { "en": "Strengths", "fa": "نقاط قوت" },
  "starken": { "en": "Strengths", "fa": "نقاط قوت" },

  "nebenkosten": { "en": "Utilities / Additional costs", "fa": "هزینه‌های جانبی" },
  "monatlich": { "en": "Monthly", "fa": "ماهانه" },
  "mietvertrag": { "en": "Lease / Rental agreement", "fa": "قرارداد اجاره" },

  "verbindung": { "en": "Connection", "fa": "اتصال" },
  "starten": { "en": "To start", "fa": "شروع کردن" },
  "bereits": { "en": "Already", "fa": "قبلاً" },
  "dringend": { "en": "Urgently", "fa": "فوری" },
  "störung": { "en": "Disruption / Malfunction", "fa": "اختلال" },
  "storung": { "en": "Disruption / Malfunction", "fa": "اختلال" },
  "voraussichtlich": { "en": "Presumably / Expected", "fa": "احتمالاً" },
  "innerhalb": { "en": "Within", "fa": "در داخل" },
  "außerdem": { "en": "Furthermore / Besides", "fa": "علاوه بر این" },
  "ausserdem": { "en": "Furthermore / Besides", "fa": "علاوه بر این" },
  "akku": { "en": "Battery", "fa": "باتری" },
  "abteilung": { "en": "Department", "fa": "بخش" },
  "rückmeldung": { "en": "Feedback / Response", "fa": "بازخورد" },
  "ruckmeldung": { "en": "Feedback / Response", "fa": "بازخورد" },
  "sobald": { "en": "As soon as", "fa": "به محض اینکه" },

  "deutschkurs": { "en": "German course", "fa": "دوره آلمانی" },
  "sprachniveau": { "en": "Language level", "fa": "سطح زبان" },
  "anfänger": { "en": "Beginner", "fa": "مبتدی" },
  "anfanger": { "en": "Beginner", "fa": "مبتدی" },
  "jede": { "en": "Every / Each", "fa": "هر" },
  "jeder": { "en": "Every / Each", "fa": "هر" },
  "jedes": { "en": "Every / Each", "fa": "هر" },
  "maximal": { "en": "Maximum", "fa": "حداکثر" },
  "semester": { "en": "Semester", "fa": "ترم" },
  "bestätigung": { "en": "Confirmation", "fa": "تأییدیه" },
  "bestatigung": { "en": "Confirmation", "fa": "تأییدیه" },
  "per": { "en": "By / Via", "fa": "از طریق" },

  "beruhigen": { "en": "To calm down", "fa": "آرام شدن" },
  "gestohlen": { "en": "Stolen", "fa": "دزدیده شده" },
  "stehlen": { "en": "To steal", "fa": "دزدیدن" },
  "dokumente": { "en": "Documents", "fa": "مدارک" },
  "dokument": { "en": "Document", "fa": "مدرک" },
  "sperren": { "en": "To block / To lock", "fa": "مسدود کردن" },
  "tourist": { "en": "Tourist", "fa": "گردشگر" },
  "botschaft": { "en": "Embassy / Message", "fa": "سفارت / پیام" },
  "daten": { "en": "Data / Details", "fa": "اطلاعات" },
  "geboren": { "en": "Born", "fa": "متولد" },
  "adresse": { "en": "Address", "fa": "آدرس" },
  "erreichen": { "en": "To reach", "fa": "رسیدن" },
  "zentrum": { "en": "Center", "fa": "مرکز" },

  "legen": { "en": "To put / To place", "fa": "گذاشتن" },
  "waage": { "en": "Scale", "fa": "ترازو" },
  "wiegt": { "en": "Weighs", "fa": "وزنش هست" },
  "wiegen": { "en": "To weigh", "fa": "وزن کردن" },
  "kilogramm": { "en": "Kilogram", "fa": "کیلوگرم" },
  "wohin": { "en": "Where to", "fa": "به کجا" },
  "geschenk": { "en": "Gift / Present", "fa": "هدیه" },
  "unterschied": { "en": "Difference", "fa": "تفاوت" },
  "lieferzeit": { "en": "Delivery time", "fa": "زمان تحویل" },
  "ordnung": { "en": "Order / Alright (in Ordnung)", "fa": "نظم / بسیار خب" },
  "versichern": { "en": "To insure", "fa": "بیمه کردن" },
  "zusätzlich": { "en": "Additional", "fa": "اضافی" },
  "zusatzlich": { "en": "Additional", "fa": "اضافی" },
  "verfolgen": { "en": "To track / To follow", "fa": "پیگیری کردن" },
  "ausgefüllt": { "en": "Filled out", "fa": "پر شده" },
  "ausgefullt": { "en": "Filled out", "fa": "پر شده" },
  "füllen": { "en": "To fill", "fa": "پر کردن" },
  "fullen": { "en": "To fill", "fa": "پر کردن" },
  "ausfüllen": { "en": "To fill out", "fa": "پر کردن (فرم)" },
  "ausfullen": { "en": "To fill out", "fa": "پر کردن (فرم)" },

  "wieder": { "en": "Again", "fa": "دوباره" },
  "licht": { "en": "Light", "fa": "نور / چراغ" },
  "andere": { "en": "Other / Another", "fa": "دیگر" },
  "anderer": { "en": "Other (masc.)", "fa": "دیگر" },
  "anderes": { "en": "Other (neut.)", "fa": "دیگر" },
  "dort": { "en": "There", "fa": "آنجا" },
  "daran": { "en": "At it / About it", "fa": "به آن" },
  "draußen": { "en": "Outside", "fa": "بیرون" },
  "draussen": { "en": "Outside", "fa": "بیرون" },
  "gleich": { "en": "Right away / Same", "fa": "همین الان / یکسان" },
  "weiter": { "en": "Further / Continue", "fa": "بیشتر / ادامه" },
  "hoch": { "en": "High / Up", "fa": "بلند / بالا" },
  "rein": { "en": "In / Pure", "fa": "داخل / خالص" },
  "danach": { "en": "After that", "fa": "بعد از آن" }
}
